README.rst
setup.py
correos_chile_express/connector.py
correos_chile_express/handler.py
correos_chile_express/settings.py
django_correos_chile_express_rest.egg-info/PKG-INFO
django_correos_chile_express_rest.egg-info/SOURCES.txt
django_correos_chile_express_rest.egg-info/dependency_links.txt
django_correos_chile_express_rest.egg-info/top_level.txt